FraxScanSDK/FraxScanApis.py
FraxScanSDK/__init__.py
FraxScanSDK-1.0.1.dist-info/METADATA
FraxScanSDK-1.0.1.dist-info/WHEEL
FraxScanSDK-1.0.1.dist-info/top_level.txt
FraxScanSDK-1.0.1.dist-info/RECORD
