Metadata-Version: 2.1
Name: FraxScanSDK
Version: 1.0.1
Summary: A python wrapper for the FraxScan API
Home-page: https://github.com/kbm9696/FraxScan-SDK
Author: Balamurugan
Author-email: kbala007.1996@gmail.com
License: GNU General Public License v3.0
Requires-Dist: requests
